dora_internvl/__init__.py
dora_internvl/main.py
dora_internvl-0.3.11.dist-info/METADATA
dora_internvl-0.3.11.dist-info/WHEEL
dora_internvl-0.3.11.dist-info/entry_points.txt
dora_internvl-0.3.11.dist-info/top_level.txt
dora_internvl-0.3.11.dist-info/RECORD
