Metadata-Version: 2.4
Name: dora-internvl
Version: 0.3.11
Summary: Dora Node for VLM
Author-email: Haixuan Xavier Tao <tao.xavier@outlook.com>, Enzo Le Van <dev@enzo-le-van.fr>
License: MIT
Requires-Python: >=3.8
Requires-Dist: dora-rs>=0.3.9
Requires-Dist: numpy<2.0.0
Requires-Dist: torch>=2.2.0
Requires-Dist: torchvision>=0.17
Requires-Dist: transformers>=4.11.3
Requires-Dist: pillow>=10.0.0
Requires-Dist: bitsandbytes>=0.41.0
Requires-Dist: einops>=0.6.1
Requires-Dist: einops-exts>=0.0.4
Requires-Dist: timm>=0.9.12
Requires-Dist: sentencepiece>=0.1.99
